setup.py
NCTU_Oauth.egg-info/PKG-INFO
NCTU_Oauth.egg-info/SOURCES.txt
NCTU_Oauth.egg-info/dependency_links.txt
NCTU_Oauth.egg-info/requires.txt
NCTU_Oauth.egg-info/top_level.txt
NCTU_Oauth.egg-info/zip-safe
nctu_oauth/__init__.py
nctu_oauth/oauth.py