Metadata-Version: 1.0
Name: NCTU-Oauth
Version: 0.1.0
Summary: adds NCTU-Oauth support to flask
Home-page: https://github.com/steven5538/NCTU-Oauth
Author: steven5538
Author-email: steven5538@gmail.com
License: BSD
Keywords: python flask nctu oauth nctu-oauth
Platform: UNKNOWN
